hypothesis_jsonschema/__init__.py
hypothesis_jsonschema/_canonicalise.py
hypothesis_jsonschema/_encode.py
hypothesis_jsonschema/_from_schema.py
hypothesis_jsonschema/_resolve.py
hypothesis_jsonschema/py.typed
hypothesis_jsonschema-0.23.0.dist-info/LICENSE
hypothesis_jsonschema-0.23.0.dist-info/METADATA
hypothesis_jsonschema-0.23.0.dist-info/WHEEL
hypothesis_jsonschema-0.23.0.dist-info/top_level.txt
hypothesis_jsonschema-0.23.0.dist-info/RECORD
