Metadata-Version: 2.1
Name: hypothesis-jsonschema
Version: 0.23.0
Summary: Generate test data from JSON schemata with Hypothesis
Home-page: https://github.com/Zac-HD/hypothesis-jsonschema
Author: Zac Hatfield-Dodds
Author-email: zac@zhd.dev
License: MPL 2.0
Project-URL: Funding, https://github.com/sponsors/Zac-HD
Keywords: python testing fuzzing property-based-testing json-schema
Classifier: Development Status :: 4 - Beta
Classifier: Framework :: Hypothesis
Classifier: Intended Audience :: Developers
Classifier: License :: OSI Approved :: Mozilla Public License 2.0 (MPL 2.0)
Classifier: Programming Language :: Python
Classifier: Programming Language :: Python :: 3
Classifier: Programming Language :: Python :: 3.8
Classifier: Programming Language :: Python :: 3.9
Classifier: Programming Language :: Python :: 3.10
Classifier: Programming Language :: Python :: 3.11
Classifier: Topic :: Education :: Testing
Classifier: Topic :: Software Development :: Testing
Classifier: Typing :: Typed
Requires-Python: >=3.8
License-File: LICENSE
Requires-Dist: hypothesis >=6.84.3
Requires-Dist: jsonschema >=4.18.0
